epab_test/__init__.py
epab_test/__main__.py
test/__init__.py
test/conftest.py
test/test_dummy.py
epab_test-2018.10.29.1.dist-info/METADATA
epab_test-2018.10.29.1.dist-info/WHEEL
epab_test-2018.10.29.1.dist-info/top_level.txt
epab_test-2018.10.29.1.dist-info/RECORD
