Metadata-Version: 2.1
Name: epab-test
Version: 2018.10.29.1
Summary: disregard this
Home-page: https://github.com/etcher-be/epab_test
Author: etcher-be
Author-email: epab@daribouca.net
License: GPLv3
Download-URL: https://github.com/etcher-be/epab_test/releases
Platform: win32
Classifier: Development Status :: 3 - Alpha
Classifier: Topic :: Utilities
Requires-Python: >=3.6
